todo/__init__.py
todo/__main__.py
todo/todo.py
todo/todo_prompt.py
the_todo-0.1.1.dist-info/LICENCE
the_todo-0.1.1.dist-info/METADATA
the_todo-0.1.1.dist-info/WHEEL
the_todo-0.1.1.dist-info/top_level.txt
the_todo-0.1.1.dist-info/RECORD
