Metadata-Version: 2.1
Name: the-todo
Version: 0.1.1
Summary: A simple command line todo application
Home-page: https://github.com/aarsh-pandey/the-todo
Author: Aarsh Pandey
Classifier: Programming Language :: Python :: 3
Classifier: Programming Language :: Python :: 3.6
Classifier: Programming Language :: Python :: 3.7
Classifier: Programming Language :: Python :: 3.8
Classifier: Programming Language :: Python :: 3.9
Classifier: Programming Language :: Python :: 3.10
Classifier: Programming Language :: Python :: 3.11
License-File: LICENCE
Requires-Dist: termcolor
